taskchain/__init__.py
taskchain/cache.py
taskchain/chain.py
taskchain/config.py
taskchain/data.py
taskchain/parameter.py
taskchain/task.py
taskchain/utils/__init__.py
taskchain/utils/clazz.py
taskchain/utils/data.py
taskchain/utils/io.py
taskchain/utils/iter.py
taskchain/utils/json.py
taskchain/utils/jupyter.py
taskchain/utils/migration.py
taskchain/utils/testing.py
taskchain/utils/threading.py
taskchain-1.4.0.dist-info/LICENSE.txt
taskchain-1.4.0.dist-info/METADATA
taskchain-1.4.0.dist-info/WHEEL
taskchain-1.4.0.dist-info/RECORD
