Metadata-Version: 2.1
Name: taskchain
Version: 1.4.0
Summary: Utility for running data and ML pipelines
Home-page: https://flowerchecker.github.io/taskchain/
License: MIT
Author:  Jiří Thran Řihák
Author-email: exthran@gmail.com
Requires-Python: >=3.8,<4.0
Classifier: License :: OSI Approved :: MIT License
Classifier: Programming Language :: Python :: 3
Classifier: Programming Language :: Python :: 3.8
Classifier: Programming Language :: Python :: 3.9
Classifier: Programming Language :: Python :: 3.10
Classifier: Programming Language :: Python :: 3.11
Requires-Dist: PyYAML (>=6.0,<7.0)
Requires-Dist: filelock (==3.12.2)
Requires-Dist: h5py (>=3.7.0,<4.0.0)
Requires-Dist: icecream (>=2.1.3,<3.0.0)
Requires-Dist: networkx (>=2.8.7,<3.0.0)
Requires-Dist: orjson (>=3.8.7,<4.0.0)
Requires-Dist: pandas (>=1.5.1,<2.0.0)
Requires-Dist: pytest (>=7.2.0,<8.0.0)
Requires-Dist: seaborn (>=0.12.1,<0.13.0)
Requires-Dist: tabulate (>=0.9.0,<0.10.0)
Requires-Dist: tqdm (>=4.64.1,<5.0.0)
Project-URL: Documentation, https://flowerchecker.github.io/taskchain/
Project-URL: Repository, https://github.com/flowerchecker/taskchain
